[
  {
    "index": 0,
    "time": "1995-01-01T00:00:00.000Z",
    "prev_hash": "",
    "hash": "dff9870f61f640f245f4ef0893afdabe5320479d59b2bb7a77e5211d6a6d0c36",
    "tx": {
      "id": "",
      "inputs": [],
      "outputs": []
    },
    "validator": {
      "addr": "",
      "signature": "",
      "token": 0
    }
  },
  {
    "index": 1,
    "time": "2023-10-20T00:58:05.030Z",
    "prev_hash": "dff9870f61f640f245f4ef0893afdabe5320479d59b2bb7a77e5211d6a6d0c36",
    "hash": "323620b4cd68efb92f0ff0ed71ebed62a58c54c52826226100e56b00cf5a337f",
    "tx": {
      "id": "17fe4ff4-b903-4173-8db6-8a424c5f0915",
      "inputs": [
        {
          "time": "2023-10-20T00:58:05.026Z",
          "from": "TaroWallet",
          "signature": "デジタル署名に同意します"
        }
      ],
      "outputs": [
        {
          "to": "HanakoWallet",
          "amount": 20,
          "fee": 3
        }
      ]
    },
    "validator": {
      "addr": "WatanabeWallet",
      "signature": "私は責任を持って取引を確認します",
      "token": 4
    }
  },
  {
    "index": 2,
    "time": "2023-10-20T00:58:28.712Z",
    "prev_hash": "323620b4cd68efb92f0ff0ed71ebed62a58c54c52826226100e56b00cf5a337f",
    "hash": "1dee23ba189b91cd35aa764a818f41d771b572ac42243a202d3bef17e48dd7e3",
    "tx": {
      "id": "8397d7ff-7ef7-46a4-8519-9a850c977948",
      "inputs": [
        {
          "time": "2023-10-20T00:58:28.709Z",
          "from": "TaroWallet",
          "signature": "デジタル署名に同意します"
        }
      ],
      "outputs": [
        {
          "to": "HanakoWallet",
          "amount": 20,
          "fee": 3
        }
      ]
    },
    "validator": {
      "addr": "TanakaWallet",
      "signature": "私は責任を持って取引を確認します",
      "token": 2
    }
  },
  {
    "index": 3,
    "time": "2023-10-20T00:58:50.922Z",
    "prev_hash": "1dee23ba189b91cd35aa764a818f41d771b572ac42243a202d3bef17e48dd7e3",
    "hash": "aaae99ee1bf79fc629f0c6269910b8017cf8db3c0d2dd051ff24feb8a690277b",
    "tx": {
      "id": "9c57332f-4c62-4ff0-998e-23a5d62f013c",
      "inputs": [
        {
          "time": "2023-10-20T00:58:50.919Z",
          "from": "TaroWallet",
          "signature": "デジタル署名に同意します"
        }
      ],
      "outputs": [
        {
          "to": "HanakoWallet",
          "amount": 20,
          "fee": 3
        }
      ]
    },
    "validator": {
      "addr": "TanakaWallet",
      "signature": "私は責任を持って取引を確認します",
      "token": 2
    }
  },
  {
    "index": 4,
    "time": "2023-10-20T00:59:05.491Z",
    "prev_hash": "aaae99ee1bf79fc629f0c6269910b8017cf8db3c0d2dd051ff24feb8a690277b",
    "hash": "56a3c38b61ff0113076771f0b1d5fd8f17b1ed6b85d0745824b216c7aded0fc3",
    "tx": {
      "id": "d99becd1-9370-43de-bbe9-f137a026f2fb",
      "inputs": [
        {
          "time": "2023-10-20T00:59:05.487Z",
          "from": "TaroWallet",
          "signature": "デジタル署名に同意します"
        }
      ],
      "outputs": [
        {
          "to": "HanakoWallet",
          "amount": 20,
          "fee": 3
        }
      ]
    },
    "validator": {
      "addr": "SaitoWallet",
      "signature": "私は責任を持って取引を確認します",
      "token": 3
    }
  }
]